sync_tool/__init__.py
sync_tool/rclone.py
zsync_tool-2024.10.1.data/data/LICENSE
zsync_tool-2024.10.1.dist-info/LICENSE
zsync_tool-2024.10.1.dist-info/METADATA
zsync_tool-2024.10.1.dist-info/WHEEL
zsync_tool-2024.10.1.dist-info/top_level.txt
zsync_tool-2024.10.1.dist-info/RECORD
