Metadata-Version: 2.1
Name: zsync-tool
Version: 2024.10.1
Summary: sync tool: rclone
Author: Xin-Xin Ma
License: GPL
Project-URL: Source, https://gitee.com/SIZXSN6/zcfg
License-File: LICENSE
Requires-Dist: loguru
